MANIFEST.in
README.md
setup.py
mweb.py.egg-info/PKG-INFO
mweb.py.egg-info/SOURCES.txt
mweb.py.egg-info/dependency_links.txt
mweb.py.egg-info/requires.txt
mweb.py.egg-info/top_level.txt
mwebapp/__init__.py
mwebapp/db.py
mwebapp/environ.py
mwebapp/httperror.py
mwebapp/orm.py
mwebapp/template_engine.py
mwebapp/webapp.py
test/main.py
test/middleware.py
test/middleware.pyc
test/models.py
test/models.pyc
test/settings.py
test/settings.pyc
test/views.py
test/views.pyc
test/static/favicon.ico
test/static/img/cat.png
test/template/base.html
test/template/index.html
test/template/other.html