Metadata-Version: 1.1
Name: mweb.py
Version: 1.2.1
Summary: Web framework written by self practice
Home-page: https://github.com/Ming-Lei/mwebapp
Author: MingLei Ji
Author-email: ming3055@foxmail.com
License: UNKNOWN
Platform: UNKNOWN
Classifier: License :: OSI Approved :: MIT License
Classifier: Programming Language :: Python
Classifier: Programming Language :: Python :: 3
